<?xml version="1.0" encoding="utf-8"?>
<cms.classpermission>
  <ClassID>
    <CodeName>Training.ContactSection</CodeName>
    <GUID>133783ef-6a86-43d1-b519-ffb7526ba272</GUID>
    <ObjectType>cms.documenttype</ObjectType>
  </ClassID>
  <PermissionDescription>{$permissiondescription.document.exploretree$}</PermissionDescription>
  <PermissionDisplayInMatrix>True</PermissionDisplayInMatrix>
  <PermissionDisplayName>{$permissionnames.exploretree$}</PermissionDisplayName>
  <PermissionGUID>71577c5f-016b-48ec-b034-1b053d39e386</PermissionGUID>
  <PermissionName>ExploreTree</PermissionName>
  <PermissionOrder>7</PermissionOrder>
</cms.classpermission>