<?xml version="1.0" encoding="utf-8"?>
<cms.macrorule>
  <MacroRuleCondition>
    <![CDATA[{_was}(Activity.ActivityValue <= (ToDouble({toval})/100) && Activity.ActivityValue >= (ToDouble({fromval})/100))]]>
  </MacroRuleCondition>
  <MacroRuleDescription>
    <![CDATA[{$macrorule.cmsactivitycontentratingperformedwitharatingbetween.description$}]]>
  </MacroRuleDescription>
  <MacroRuleDisplayName>
    <![CDATA[Activity 'Content rating' performed with a rating between]]>
  </MacroRuleDisplayName>
  <MacroRuleEnabled>True</MacroRuleEnabled>
  <MacroRuleGUID>6e7e37cc-8989-4aab-8776-fbd86d448481</MacroRuleGUID>
  <MacroRuleIsCustom>False</MacroRuleIsCustom>
  <MacroRuleName>
    <![CDATA[CMSActivityContentRatingPerformedWithARatingBetween]]>
  </MacroRuleName>
  <MacroRuleParameters>
    <form version="2">
      <field column="toval" columntype="integer" guid="563668ef-7e05-4cea-8905-9a5beef10e71" publicfield="false" visibility="none" visible="true">
        <properties>
          <fieldcaption>choose percentage value</fieldcaption>
          <validationerrormessage>{$general.percentagebetween$}</validationerrormessage>
        </properties>
        <settings>
          <AutoCompleteEnableCaching>False</AutoCompleteEnableCaching>
          <AutoCompleteFirstRowSelected>False</AutoCompleteFirstRowSelected>
          <AutoCompleteShowOnlyCurrentWordInCompletionListItem>False</AutoCompleteShowOnlyCurrentWordInCompletionListItem>
          <controlname>textboxcontrol</controlname>
          <FilterMode>False</FilterMode>
          <Trim>False</Trim>
        </settings>
        <rules>
          <rule>
            <![CDATA[{%Rule("Value >= 0", "<rules><r pos=\"0\" par=\"\" op=\"and\" n=\"MinValue\" ><p n=\"minvalue\"><t>0</t><v>0</v><r>false</r><d></d><vt>integer</vt></p></r></rules>")%}]]>
          </rule>
          <rule>
            <![CDATA[{%Rule("Value <= 100", "<rules><r pos=\"0\" par=\"\" op=\"and\" n=\"MaxValue\" ><p n=\"maxvalue\"><t>100</t><v>100</v><r>false</r><d></d><vt>integer</vt></p></r></rules>")%}]]>
          </rule>
        </rules>
      </field>
      <field allowempty="true" column="_was" columnsize="100" columntype="text" guid="6c51e580-d5f2-4d42-a044-6d43e4aa1e09" publicfield="false" visibility="none" visible="true">
        <properties>
          <defaultvalue>;was</defaultvalue>
          <fieldcaption>select operation</fieldcaption>
        </properties>
        <settings>
          <controlname>macronegationoperator</controlname>
          <Options>
<![CDATA[
;was
!;was not
]]>
          </Options>
          <RepeatDirection>horizontal</RepeatDirection>
        </settings>
      </field>
      <field column="fromval" columntype="integer" guid="8035b5b4-0e0c-4bb9-b5eb-4e7351524391" publicfield="false" visibility="none" visible="true">
        <properties>
          <fieldcaption>choose percentage value</fieldcaption>
          <validationerrormessage>{$general.percentagebetween$}</validationerrormessage>
        </properties>
        <settings>
          <AutoCompleteEnableCaching>False</AutoCompleteEnableCaching>
          <AutoCompleteFirstRowSelected>False</AutoCompleteFirstRowSelected>
          <AutoCompleteShowOnlyCurrentWordInCompletionListItem>False</AutoCompleteShowOnlyCurrentWordInCompletionListItem>
          <controlname>textboxcontrol</controlname>
          <FilterMode>False</FilterMode>
          <Trim>False</Trim>
        </settings>
        <rules>
          <rule>
            <![CDATA[{%Rule("Value >= 0", "<rules><r pos=\"0\" par=\"\" op=\"and\" n=\"MinValue\" ><p n=\"minvalue\"><t>0</t><v>0</v><r>false</r><d></d><vt>integer</vt></p></r></rules>")%}]]>
          </rule>
          <rule>
            <![CDATA[{%Rule("Value <= 100", "<rules><r pos=\"0\" par=\"\" op=\"and\" n=\"MaxValue\" ><p n=\"maxvalue\"><t>100</t><v>100</v><r>false</r><d></d><vt>integer</vt></p></r></rules>")%}]]>
          </rule>
        </rules>
      </field>
    </form>
  </MacroRuleParameters>
  <MacroRuleRequiredData>Activity</MacroRuleRequiredData>
  <MacroRuleRequiresContext>False</MacroRuleRequiresContext>
  <MacroRuleResourceName>cms.onlinemarketing</MacroRuleResourceName>
  <MacroRuleText>
    <![CDATA[Activity 'Content rating' {_was} performed with a rating value between {fromval}% and {toval}%]]>
  </MacroRuleText>
</cms.macrorule>