<?xml version="1.0" encoding="utf-8"?>
<reporting.reportvalue>
  <ValueDisplayName>Report not available caption</ValueDisplayName>
  <ValueFormatString />
  <ValueGUID>d7e539e1-ad6c-4615-a7d5-ed2e4066ad7a</ValueGUID>
  <ValueName>NotAvailableCaption</ValueName>
  <ValueQuery>
<![CDATA[
IF (@BannerId IS NULL)
BEGIN
  SELECT '{$bannermanagement.reportnotavailable.caption$}: {$bannermanagement.reportnotavailable.description$}'
END
]]>
  </ValueQuery>
  <ValueQueryIsStoredProcedure>False</ValueQueryIsStoredProcedure>
  <ValueReportID>
    <CodeName>bannerhitsclicks.weekreport</CodeName>
    <GUID>ddf8f91e-462e-4d7a-b5dd-f0475ab5c290</GUID>
    <ObjectType>reporting.report</ObjectType>
  </ValueReportID>
  <ValueSettings>
    <CustomData>
      <subscriptionenabled>True</subscriptionenabled>
    </CustomData>
  </ValueSettings>
</reporting.reportvalue>