<?xml version="1.0" encoding="utf-8"?>
<cms.allowedchildclass>
  <Parent>
    <CodeName>Training.DoctorSection</CodeName>
    <GUID>5306b221-73ff-4d18-bc06-a0edcec1ad7d</GUID>
    <ObjectType>cms.documenttype</ObjectType>
  </Parent>
  <Bindings>
    <Binding id="cms.documenttype_CMS.Root">
      <ParentClassID>
        <CodeName>CMS.Root</CodeName>
        <GUID>a585aea3-10b5-4b74-9aad-747fcce72493</GUID>
        <ObjectType>cms.documenttype</ObjectType>
      </ParentClassID>
    </Binding>
  </Bindings>
</cms.allowedchildclass>