<?xml version="1.0" encoding="utf-8"?>
<cms.uielement>
  <ElementAccessCondition />
  <ElementCaption>{$content.ui.variant$}</ElementCaption>
  <ElementCheckModuleReadPermission>False</ElementCheckModuleReadPermission>
  <ElementDescription />
  <ElementDisplayName>{$content.ui.variant$}</ElementDisplayName>
  <ElementFeature />
  <ElementFromVersion>6.0</ElementFromVersion>
  <ElementGUID>681fd60c-4998-41eb-8c10-91e03f0ce242</ElementGUID>
  <ElementIsCustom>False</ElementIsCustom>
  <ElementIsGlobalApplication>False</ElementIsGlobalApplication>
  <ElementIsMenu>False</ElementIsMenu>
  <ElementName>WebPartProperties.Variant</ElementName>
  <ElementOrder>5</ElementOrder>
  <ElementParentID>
    <CodeName>Design.WebPartProperties</CodeName>
    <GUID>68453d64-cbed-4917-9801-46e7f0d07676</GUID>
    <ObjectType>cms.uielement</ObjectType>
    <Parent>
      <CodeName>CMS.Design</CodeName>
      <GUID>b755e8fc-a06f-421a-b749-f2d31d1f2570</GUID>
      <ObjectType>cms.resource</ObjectType>
    </Parent>
  </ElementParentID>
  <ElementProperties />
  <ElementRequiresGlobalAdminPriviligeLevel>False</ElementRequiresGlobalAdminPriviligeLevel>
  <ElementResourceID>
    <CodeName>CMS.Design</CodeName>
    <GUID>b755e8fc-a06f-421a-b749-f2d31d1f2570</GUID>
    <ObjectType>cms.resource</ObjectType>
  </ElementResourceID>
  <ElementSize>0</ElementSize>
  <ElementTargetURL>
    <![CDATA[~/CMSModules/OnlineMarketing/Pages/WebParts/WebPartProperties_personalized_frameset.aspx?{??}&varianttype=webpart]]>
  </ElementTargetURL>
  <ElementType>Url</ElementType>
  <ElementVisibilityCondition />
</cms.uielement>