<?xml version="1.0" encoding="utf-8"?>
<cms.uielement>
  <ElementCaption>{$friends.userrejectedfriendships$}</ElementCaption>
  <ElementCheckModuleReadPermission>True</ElementCheckModuleReadPermission>
  <ElementDisplayName>{$friends.userrejectedfriendships$}</ElementDisplayName>
  <ElementFromVersion>8.0</ElementFromVersion>
  <ElementGUID>9bc39cdd-03fa-49de-85a5-6fa2b2cedfb5</ElementGUID>
  <ElementIsCustom>False</ElementIsCustom>
  <ElementIsGlobalApplication>False</ElementIsGlobalApplication>
  <ElementIsMenu>False</ElementIsMenu>
  <ElementName>SMFriendsRejectedFriends</ElementName>
  <ElementOrder>3</ElementOrder>
  <ElementParentID>
    <CodeName>Friends</CodeName>
    <GUID>1235f100-cf6c-43de-bf9d-202033ae0433</GUID>
    <ObjectType>cms.uielement</ObjectType>
    <Parent>
      <CodeName>CMS.Friends</CodeName>
      <GUID>d6f94476-424a-4aed-ad22-c34a32cbc1d8</GUID>
      <ObjectType>cms.resource</ObjectType>
    </Parent>
  </ElementParentID>
  <ElementProperties>
    <data>
      <includejquery>False</includejquery>
      <category_name_header>False</category_name_header>
      <displaybreadcrumbs>False</displaybreadcrumbs>
    </data>
  </ElementProperties>
  <ElementRequiresGlobalAdminPriviligeLevel>False</ElementRequiresGlobalAdminPriviligeLevel>
  <ElementResourceID>
    <CodeName>CMS.Friends</CodeName>
    <GUID>d6f94476-424a-4aed-ad22-c34a32cbc1d8</GUID>
    <ObjectType>cms.resource</ObjectType>
  </ElementResourceID>
  <ElementSize>0</ElementSize>
  <ElementTargetURL>
    <![CDATA[~/CMSModules/Friends/Administration/Users/User_Edit_Friends_Rejected.aspx]]>
  </ElementTargetURL>
  <ElementType>Url</ElementType>
</cms.uielement>