<?xml version="1.0" encoding="utf-8"?>
<cms.webpart>
  <WebPartCategoryID>
    <CodeName>SyndicationRSS</CodeName>
    <GUID>fcec1ff1-21ce-48d3-8a63-3d96de0c5ccf</GUID>
    <ObjectType>cms.webpartcategory</ObjectType>
  </WebPartCategoryID>
  <WebPartDefaultConfiguration>
    <page />
  </WebPartDefaultConfiguration>
  <WebPartDefaultValues />
  <WebPartDescription>
    <![CDATA[This web part creates an RSS feed of Kentico events. Uses a built-in pre-configured pages data source as a source of the events. Displays a link leading to the feed, which is located at the URL of the page where the web part is placed, with a querystring parameter appended.]]>
  </WebPartDescription>
  <WebPartDisplayName>Events RSS feed</WebPartDisplayName>
  <WebPartFileName>CMS RSS Feed</WebPartFileName>
  <WebPartGUID>9feda7ae-d2a3-43a5-9af8-abfcc7e04e81</WebPartGUID>
  <WebPartIconClass>icon-w-events-rss-feed</WebPartIconClass>
  <WebPartName>EventsRSSFeed</WebPartName>
  <WebPartParentID>
    <CodeName>CMSRSSFeed</CodeName>
    <GUID>cd73955d-79c2-41cc-9dfc-84c53f6a5b6e</GUID>
    <ObjectType>cms.webpart</ObjectType>
  </WebPartParentID>
  <WebPartProperties>
    <form version="2">
      <field column="LinkText" guid="a526fda9-647b-4edd-8947-f288965a9d2d">
        <settings>
          <AutoCompleteEnableCaching>False</AutoCompleteEnableCaching>
          <AutoCompleteFirstRowSelected>False</AutoCompleteFirstRowSelected>
          <AutoCompleteShowOnlyCurrentWordInCompletionListItem>False</AutoCompleteShowOnlyCurrentWordInCompletionListItem>
          <Trim>False</Trim>
        </settings>
        <properties>
          <defaultvalue>Upcoming events RSS</defaultvalue>
        </properties>
      </field>
      <field column="LinkIcon" guid="2495bd2a-71c5-4599-a15a-d05ddd6dc620" />
      <field column="EnableRSSAutodiscovery" guid="2d9639d7-ce1f-4be7-8ac3-3a9eb420d8e0" />
      <field column="FeedName" guid="7dd88605-7f7c-49c1-b420-612c34280d96">
        <properties>
          <defaultvalue>events</defaultvalue>
        </properties>
      </field>
      <field column="FeedTitle" guid="02ea6032-e5bc-4ad6-b171-8cf3700bb520">
        <settings>
          <AutoCompleteEnableCaching>False</AutoCompleteEnableCaching>
          <AutoCompleteFirstRowSelected>False</AutoCompleteFirstRowSelected>
          <AutoCompleteShowOnlyCurrentWordInCompletionListItem>False</AutoCompleteShowOnlyCurrentWordInCompletionListItem>
          <Trim>False</Trim>
        </settings>
        <properties>
          <defaultvalue>Events</defaultvalue>
        </properties>
      </field>
      <field column="FeedDescription" guid="b93c4faa-d7da-4223-a70d-757cf944403f" />
      <field column="FeedLanguage" guid="a48b6d99-ac6e-4e6f-937a-edf17ece7f74" />
      <field column="QueryStringKey" guid="b7939bd3-7e28-4b97-929f-fddada90da0c" />
      <field column="HeaderXML" guid="31e9b748-1e3f-4ec7-b00e-2d199be7ae4b" />
      <field column="FooterXML" guid="3dcf3694-6a69-4931-8e99-bb497354ec5d" />
      <field column="Path" guid="d1dc26d0-211a-4e15-b652-242a23b38f62" />
      <field column="TransformationName" guid="e6c86dd8-a1ac-4782-841b-2dc263b6bdd9">
        <properties>
          <defaultvalue>cms.bookingevent.rssitem</defaultvalue>
        </properties>
      </field>
      <field column="ClassNames" guid="a23bab61-2481-4663-895e-fc53cd416bff" reftype="">
        <settings>
          <SelectionMode>0</SelectionMode>
        </settings>
        <properties>
          <defaultvalue>cms.bookingevent</defaultvalue>
        </properties>
      </field>
      <field column="CombineWithDefaultCulture" guid="0839ea6e-ff4b-4cd7-a012-887e39f26786" />
      <field column="CultureCode" guid="564ab35e-3658-4b97-be89-e823af4e1551" />
      <field column="MaxRelativeLevel" guid="90572295-3e55-495b-aee1-533fc1473b7c" />
      <field column="OrderBy" guid="643dee71-7339-4a60-a7ea-3f1cb3d72151">
        <properties>
          <defaultvalue>EventDate DESC</defaultvalue>
        </properties>
      </field>
      <field column="SelectOnlyPublished" guid="0c341d80-c3b9-4ddb-a020-b4c2d58038a2" />
      <field column="SelectTopN" guid="8c859b6f-5eaa-47e3-a905-8da5a6ccba7d" />
      <field column="SiteName" guid="11b04f5c-b17f-4150-96aa-4a4f1047f2b6" />
      <field column="WhereCondition" guid="a1fb320f-c3d3-4f81-ab88-906e013300d4" />
      <field column="SelectedColumns" guid="669d41ce-d717-452d-a79c-4d9c7b0c3a7b" />
      <field column="FilterOutDuplicates" guid="850ea75a-581f-46d0-a5fd-1fa8c8f1d280" />
      <field column="CheckPermissions" guid="090b54c8-c833-4c8e-b901-8d0b51798fac" />
      <field column="CacheItemName" guid="fe788261-44b1-4896-944a-9c2e3961c2a9" />
      <field column="CacheMinutes" guid="6b6bded8-4f40-4b2d-86da-9727870851c5" />
      <field column="CacheDependencies" guid="49858114-49e4-4794-b241-20eca9d41362" />
    </form>
  </WebPartProperties>
  <WebPartSkipInsertProperties>False</WebPartSkipInsertProperties>
  <WebPartType>5</WebPartType>
</cms.webpart>