<?xml version="1.0" encoding="utf-8"?>
<cms.documenttype>
  <ClassConnectionString>CMSConnectionString</ClassConnectionString>
  <ClassContactOverwriteEnabled>False</ClassContactOverwriteEnabled>
  <ClassCreateSKU>False</ClassCreateSKU>
  <ClassCustomizedColumns />
  <ClassDefaultObjectType />
  <ClassDisplayName>Root</ClassDisplayName>
  <ClassFormDefinition>
    <form version="2" />
  </ClassFormDefinition>
  <ClassFormLayout />
  <ClassFormLayoutType>html</ClassFormLayoutType>
  <ClassGUID>a585aea3-10b5-4b74-9aad-747fcce72493</ClassGUID>
  <ClassIconClass>icon-layout</ClassIconClass>
  <ClassIsContentOnly>False</ClassIsContentOnly>
  <ClassIsCoupledClass>False</ClassIsCoupledClass>
  <ClassIsCustomTable>False</ClassIsCustomTable>
  <ClassIsDocumentType>True</ClassIsDocumentType>
  <ClassIsForm>False</ClassIsForm>
  <ClassIsMenuItemType>True</ClassIsMenuItemType>
  <ClassIsProduct>False</ClassIsProduct>
  <ClassIsProductSection>False</ClassIsProductSection>
  <ClassName>CMS.Root</ClassName>
  <ClassNodeAliasSource />
  <ClassNodeNameSource />
  <ClassSearchContentColumn>DocumentContent</ClassSearchContentColumn>
  <ClassSearchCreationDateColumn>DocumentCreatedWhen</ClassSearchCreationDateColumn>
  <ClassSearchEnabled>True</ClassSearchEnabled>
  <ClassSearchImageColumn />
  <ClassSearchSettings>
    <search />
  </ClassSearchSettings>
  <ClassSearchTitleColumn>DocumentName</ClassSearchTitleColumn>
  <ClassShowAsSystemTable>False</ClassShowAsSystemTable>
  <ClassShowColumns />
  <ClassShowTemplateSelection>False</ClassShowTemplateSelection>
  <ClassTableName />
  <ClassUsePublishFromTo>False</ClassUsePublishFromTo>
  <ClassUsesVersioning>False</ClassUsesVersioning>
</cms.documenttype>