<?xml version="1.0" encoding="utf-8"?>
<cms.documenttype>
  <ClassCodeGenerationSettings>
    <Data>
      <NameSpace>Training</NameSpace>
    </Data>
  </ClassCodeGenerationSettings>
  <ClassDisplayName>Doctor</ClassDisplayName>
  <ClassFormDefinition>
    <form version="2">
      <field column="DoctorID" columntype="integer" guid="25c84309-3c07-492f-8a56-885897641bb6" isPK="true" publicfield="false">
        <properties>
          <fieldcaption>DoctorID</fieldcaption>
        </properties>
        <settings>
          <controlname>labelcontrol</controlname>
        </settings>
      </field>
      <field column="DoctorFirstName" columnsize="200" columntype="text" guid="37e724ba-281d-4f8f-866b-1713f570b795" publicfield="false" visible="true">
        <properties>
          <fieldcaption>First name</fieldcaption>
        </properties>
        <settings>
          <AutoCompleteEnableCaching>False</AutoCompleteEnableCaching>
          <AutoCompleteFirstRowSelected>False</AutoCompleteFirstRowSelected>
          <AutoCompleteShowOnlyCurrentWordInCompletionListItem>False</AutoCompleteShowOnlyCurrentWordInCompletionListItem>
          <controlname>TextBoxControl</controlname>
          <FilterMode>False</FilterMode>
          <Trim>False</Trim>
        </settings>
      </field>
      <field column="DoctorLastName" columnsize="200" columntype="text" guid="9f9b26af-6978-4a3d-938a-a5f8b8246584" publicfield="false" visible="true">
        <properties>
          <fieldcaption>Last name</fieldcaption>
        </properties>
        <settings>
          <AutoCompleteEnableCaching>False</AutoCompleteEnableCaching>
          <AutoCompleteFirstRowSelected>False</AutoCompleteFirstRowSelected>
          <AutoCompleteShowOnlyCurrentWordInCompletionListItem>False</AutoCompleteShowOnlyCurrentWordInCompletionListItem>
          <controlname>TextBoxControl</controlname>
          <FilterMode>False</FilterMode>
          <Trim>False</Trim>
        </settings>
      </field>
      <field column="DoctorDegree" columnsize="100" columntype="text" guid="10bab721-d2c3-4dc1-878f-b759b6ea9789" publicfield="false" visible="true">
        <properties>
          <fieldcaption>Doctor degree</fieldcaption>
        </properties>
        <settings>
          <AutoCompleteEnableCaching>False</AutoCompleteEnableCaching>
          <AutoCompleteFirstRowSelected>False</AutoCompleteFirstRowSelected>
          <AutoCompleteShowOnlyCurrentWordInCompletionListItem>False</AutoCompleteShowOnlyCurrentWordInCompletionListItem>
          <controlname>TextBoxControl</controlname>
          <FilterMode>False</FilterMode>
          <Trim>False</Trim>
        </settings>
      </field>
      <field column="DoctorImage" columntype="file" guid="c0446066-da1c-4442-b7d4-c81c481f386a" publicfield="false" visible="true">
        <properties>
          <fieldcaption>Photo</fieldcaption>
        </properties>
        <settings>
          <Allowed_Extensions>
            <![CDATA[pdf;doc;docx;ppt;pptx;xls;xlsx;htm;html;xml;bmp;gif;jpg;jpeg;png;wav;wma;wmv;mp3;mp4;mpg;mpeg;mov;avi;swf;rar;zip;txt;rtf]]>
          </Allowed_Extensions>
          <controlname>DirectUploadControl</controlname>
          <Extensions>inherit</Extensions>
        </settings>
      </field>
      <field column="DoctorSpecialty" columnsize="200" columntype="text" guid="7a0eae2d-391c-4513-927c-b4a33ba7e801" publicfield="false" visible="true">
        <properties>
          <fieldcaption>Doctor specialty</fieldcaption>
        </properties>
        <settings>
          <AutoCompleteEnableCaching>False</AutoCompleteEnableCaching>
          <AutoCompleteFirstRowSelected>False</AutoCompleteFirstRowSelected>
          <AutoCompleteShowOnlyCurrentWordInCompletionListItem>False</AutoCompleteShowOnlyCurrentWordInCompletionListItem>
          <controlname>TextBoxControl</controlname>
          <FilterMode>False</FilterMode>
          <Trim>False</Trim>
        </settings>
      </field>
      <field allowempty="true" column="DoctorBio" columntype="longtext" guid="a3a27d6f-e4ef-473d-850d-8ae95366e617" publicfield="false" visible="true">
        <properties>
          <fieldcaption>Bio</fieldcaption>
        </properties>
        <settings>
          <controlname>HtmlAreaControl</controlname>
          <Dialogs_Content_Hide>False</Dialogs_Content_Hide>
          <HeightUnitType>PX</HeightUnitType>
          <MediaDialogConfiguration>True</MediaDialogConfiguration>
          <ShowAddStampButton>False</ShowAddStampButton>
          <WidthUnitType>PX</WidthUnitType>
        </settings>
      </field>
      <field column="DoctorEmergencyShift" columnsize="75" columntype="text" guid="dcee62ce-160c-43ee-aa0f-60c1b6e2fa74" publicfield="false" visible="true">
        <properties>
          <fieldcaption>Emergency shift</fieldcaption>
        </properties>
        <settings>
          <controlname>DropDownListControl</controlname>
          <DisplayActualValueAsItem>False</DisplayActualValueAsItem>
          <EditText>False</EditText>
          <Options>
<![CDATA[
1;Monday
2;Tuesday
3;Wednesday
4;Thursday
5;Friday
6;Saturday
7;Sunday
]]>
          </Options>
          <SortItems>False</SortItems>
        </settings>
      </field>
    </form>
  </ClassFormDefinition>
  <ClassGUID>e6bdfa0a-1854-4415-8282-d885f7e41c8f</ClassGUID>
  <ClassIconClass>icon-user-frame</ClassIconClass>
  <ClassInheritsFromClassID>0</ClassInheritsFromClassID>
  <ClassIsContentOnly>True</ClassIsContentOnly>
  <ClassIsCoupledClass>True</ClassIsCoupledClass>
  <ClassIsCustomTable>False</ClassIsCustomTable>
  <ClassIsDocumentType>True</ClassIsDocumentType>
  <ClassIsForm>False</ClassIsForm>
  <ClassIsMenuItemType>False</ClassIsMenuItemType>
  <ClassName>Training.Doctor</ClassName>
  <ClassNodeAliasSource>DoctorLastName</ClassNodeAliasSource>
  <ClassNodeNameSource>DoctorLastName</ClassNodeNameSource>
  <ClassSearchContentColumn>DocumentContent</ClassSearchContentColumn>
  <ClassSearchCreationDateColumn>DocumentCreatedWhen</ClassSearchCreationDateColumn>
  <ClassSearchEnabled>True</ClassSearchEnabled>
  <ClassSearchSettings>
    <search>
      <item azurecontent="True" azureretrievable="False" azuresearchable="True" content="True" id="13bab4fd-0745-414b-abaf-698309469a51" name="DoctorFirstName" searchable="False" tokenized="True" />
      <item azurecontent="False" azureretrievable="True" azuresearchable="False" content="False" id="3a498b57-4ed4-428a-9006-960286a9f205" name="DoctorID" searchable="True" tokenized="False" />
      <item azurecontent="True" azureretrievable="False" azuresearchable="True" content="True" id="5ea59149-cd24-4a2c-8449-7fbbfc924270" name="DoctorBio" searchable="False" tokenized="True" />
      <item azurecontent="True" azureretrievable="False" azuresearchable="True" content="True" id="c53591fa-5329-428e-b776-7584b5a239ec" name="DoctorLastName" searchable="False" tokenized="True" />
      <item azurecontent="False" azureretrievable="False" azuresearchable="False" content="False" id="f9f6a4e9-3c55-4fda-ad8b-7096cca19d15" name="DoctorImage" searchable="False" tokenized="False" />
    </search>
  </ClassSearchSettings>
  <ClassSearchTitleColumn>DocumentName</ClassSearchTitleColumn>
  <ClassShowAsSystemTable>False</ClassShowAsSystemTable>
  <ClassTableName>Training_Doctor</ClassTableName>
  <ClassUsePublishFromTo>True</ClassUsePublishFromTo>
  <ClassUsesVersioning>False</ClassUsesVersioning>
</cms.documenttype>